priority_encoder/priority_encoder.v
/// priotity encoder


module priority_encoder(
	input[3:0] data,
	output reg [1:0] out,
	output reg valid
);

always @(*)
begin
	valid = 1'b0; // default :no input
	out = 2'b00;  // default output

	if(data[3])
	begin // highest prio
		out = 2'b11;
		valid = 1'b1;
	end
	else if(data[2])
	begin
		out = 2'b10;
		valid = 1'b1;
	end
	else if(data[1])
	begin
		out = 2'b01;
		valid = 1'b1;
	end
	else if(data[0])
	begin // lowest prio
		out = 2'b00;
		valid = 1'b1;
	end
end
endmodule

priority_encoder/priority_encoder_tb.v
// priority encoder testbench
// note: jeni vadhare priority enu output aavse


`timescale 1ns/ 1ps

module priority_encoder_tb;
	reg[3:0] data_in;
	wire [1:0] out;
	wire valid;

	// instantiating priority encoder func
	
	priority_encoder uut (.data(data_in), .out(out), .valid(valid));

	initial
	begin
		$dumpfile("priority_encoder.vcd");
		$dumpvars(0, priority_encoder_tb);

		$monitor("Time = %0t | data_in= %b | out = %b | valid = %b", $time, data_in, out, valid);

		// test cases begin
		data_in = 4'b0000; #10; // no valid i/p
		data_in = 4'b0001; #10;	// low prio
		data_in = 4'b0010; #10;
		data_in = 4'b0100; #10;
		data_in = 4'b1000; #10;

		// random test based on priority check
		//

		data_in = 4'b1010; #10;
		data_in = 4'b0111; #10;
		data_in = 4'b1111; #10;

		$finish;
	end
endmodule

priority_encoder/priority_encoder.vcd
$date
	Tue Feb 18 00:15:34 2025
$end
$version
	Icarus Verilog
$end
$timescale
	1ps
$end
$scope module priority_encoder_tb $end
$var wire 2 ! out [1:0] $end
$var wire 1 " valid $end
$var reg 4 # data_in [3:0] $end
$scope module uut $end
$var wire 4 $ data [3:0] $end
$var reg 2 % out [1:0] $end
$var reg 1 & valid $end
$upscope $end
$upscope $end
$enddefinitions $end
#0
$dumpvars
0&
b0 %
b0 $
b0 #
0"
b0 !
$end
#10000
1&
1"
b1 #
b1 $
#20000
b1 %
b1 !
1&
1"
b10 #
b10 $
#30000
b10 %
b10 !
1&
1"
b100 #
b100 $
#40000
b11 %
b11 !
1&
1"
b1000 #
b1000 $
#50000
b11 %
b11 !
1&
1"
b1010 #
b1010 $
#60000
b10 %
b10 !
1&
1"
b111 #
b111 $
#70000
b11 %
b11 !
1&
1"
b1111 #
b1111 $
