mux8x1_using_2x1/mux8x1_using2x1.v
// creating the 8x1 mux using the 2x1 mux
//

module mux2x1(input a, input b, input select, output out);
// using dataflow modeling
	assign out = select ? b : a;
endmodule

module mux8x1(input [7:0]D, input [2:0]select, output out);
wire y0, y1, y2, y3, y4, y5; //mux connector

// stage1: first four mux which select under select[0]

	mux2x1 m1(D[0], D[1], select[0], y0);
	mux2x1 m2(D[2], D[3], select[0], y1);
	mux2x1 m3(D[4], D[5], select[0], y2);
	mux2x1 m4(D[6], D[7], select[0], y3);

// stage2: another 2 mux for taking of value of above 4 mux
// we giving the input value of y0 - y3 and take output in y4 and y5

	mux2x1 m5(y0, y1, select[1], y4);
	mux2x1 m6(y2, y3, select[1], y5);

// stage3: giving above mux output value to next final mux's input

	mux2x1 m7(y4, y5, select[2], out);

endmodule

mux8x1_using_2x1/mux8x1_tb.v
// TB for 8x1 mux 

`timescale 1ns/1ps
module mux8x1_tb;

reg [7:0]a;
reg [2:0]select;

wire out;

// take instant

mux8x1 uut(.D(a), .select(select), .out(out));

initial 
begin
	$dumpfile("mux8x1_wave.vcd");
	$dumpvars(0, mux8x1_tb);

	$display("staring giving inputs");

	$monitor("a=%b, select=%b, out=%b", a, select, out);

	a = 8'b10101101; // inputs
	// a0 = 1, a1 = 0 ... a7 = 1
	
// test case: changing select lines

	select = 3'b000; #10; // select a0 (out = 1)
	select = 3'b001; #10; // select a1 (out = 0)
	select = 3'b010; #10; // select a2 (out = 1)
	select = 3'b011; #10; // select a3 (out = 1)
	select = 3'b100; #10; // select a4 (out = 0)
	select = 3'b101; #10; // select a5 (out = 1)
	select = 3'b110; #10; // select a6 (out = 0)
	select = 3'b111; #10; // select a8 (out = 1)

	$finish; // ending simulation


end
endmodule

mux8x1_using_2x1/mux8x1_wave.vcd
$date
	Fri Feb 14 02:30:00 2025
$end
$version
	Icarus Verilog
$end
$timescale
	1ps
$end
$scope module mux8x1_tb $end
$var wire 1 ! out $end
$var reg 8 " a [7:0] $end
$var reg 3 # select [2:0] $end
$scope module uut $end
$var wire 8 $ D [7:0] $end
$var wire 1 ! out $end
$var wire 3 % select [2:0] $end
$var wire 1 & y0 $end
$var wire 1 ' y1 $end
$var wire 1 ( y2 $end
$var wire 1 ) y3 $end
$var wire 1 * y4 $end
$var wire 1 + y5 $end
$scope module m1 $end
$var wire 1 , a $end
$var wire 1 - b $end
$var wire 1 & out $end
$var wire 1 . select $end
$upscope $end
$scope module m2 $end
$var wire 1 / a $end
$var wire 1 0 b $end
$var wire 1 ' out $end
$var wire 1 1 select $end
$upscope $end
$scope module m3 $end
$var wire 1 2 a $end
$var wire 1 3 b $end
$var wire 1 ( out $end
$var wire 1 4 select $end
$upscope $end
$scope module m4 $end
$var wire 1 5 a $end
$var wire 1 6 b $end
$var wire 1 ) out $end
$var wire 1 7 select $end
$upscope $end
$scope module m5 $end
$var wire 1 & a $end
$var wire 1 ' b $end
$var wire 1 * out $end
$var wire 1 8 select $end
$upscope $end
$scope module m6 $end
$var wire 1 ( a $end
$var wire 1 ) b $end
$var wire 1 + out $end
$var wire 1 9 select $end
$upscope $end
$scope module m7 $end
$var wire 1 * a $end
$var wire 1 + b $end
$var wire 1 ! out $end
$var wire 1 : select $end
$upscope $end
$upscope $end
$upscope $end
$enddefinitions $end
#0
$dumpvars
0:
09
08
07
16
05
04
13
02
01
10
1/
0.
0-
1,
0+
1*
0)
0(
1'
1&
b0 %
b10101101 $
b0 #
b10101101 "
1!
$end
#10000
0!
0*
1+
0&
1(
1)
1.
11
14
17
b1 #
b1 %
#20000
0+
1!
1&
0(
0)
1*
0.
01
04
07
18
19
b10 #
b10 %
#30000
1+
0&
1(
1)
1.
11
14
17
b11 #
b11 %
#40000
0!
0+
1&
0(
0)
1*
0.
01
04
07
08
09
1:
b100 #
b100 %
#50000
1!
0*
1+
0&
1(
1)
1.
11
14
17
b101 #
b101 %
#60000
0!
0+
1&
0(
0)
1*
0.
01
04
07
18
19
b110 #
b110 %
#70000
1!
1+
0&
1(
1)
1.
11
14
17
b111 #
b111 %
