parity_generator/parity_generator.v
// parity_generator
//
//


module parity_generator(
	input wire d2, d1, d0,
	output wire parity
);

assign parity = d2 ^ d1 ^ d0;

endmodule

parity_generator/parity_generator_tb.v
// parity generator test betch
//

`timescale 1ns/1ps

module parity_generator_tb;
reg d2, d1, d0;
wire parity;

// instatiate the main module

parity_generator uut(.d2(d2), .d1(d1), .d0(d0), .parity(parity));

initial 
begin
	$dumpfile("parity_generator_wave.vcd");
	$dumpvars(0, parity_generator_tb);
	$monitor("time: %t | d2: %b | d1: %b | d0: %b | parity: %b ", $time, d2, d1, d0, parity);

	// writing all test case for 3 bit (truth-table)
	
	d2 = 0; d1 = 0; d0 = 0; #10;
	d2 = 0; d1 = 0; d0 = 1; #10;
	d2 = 0; d1 = 1; d0 = 0; #10;
	d2 = 0; d1 = 1; d0 = 1; #10;
	d2 = 1; d1 = 0; d0 = 0; #10;
	d2 = 1; d1 = 0; d0 = 1; #10;
	d2 = 1; d1 = 1; d0 = 0; #10;
	d2 = 1; d1 = 1; d0 = 1; #10;

	$finish;
end
endmodule

parity_generator/parity_generator_wave.vcd
$date
	Tue Feb 18 23:56:53 2025
$end
$version
	Icarus Verilog
$end
$timescale
	1ps
$end
$scope module parity_generator_tb $end
$var wire 1 ! parity $end
$var reg 1 " d0 $end
$var reg 1 # d1 $end
$var reg 1 $ d2 $end
$scope module uut $end
$var wire 1 % d0 $end
$var wire 1 & d1 $end
$var wire 1 ' d2 $end
$var wire 1 ! parity $end
$upscope $end
$upscope $end
$enddefinitions $end
#0
$dumpvars
0'
0&
0%
0$
0#
0"
0!
$end
#10000
1!
1"
1%
#20000
0"
0%
1#
1&
#30000
0!
1"
1%
#40000
1!
0"
0%
0#
0&
1$
1'
#50000
0!
1"
1%
#60000
0"
0%
1#
1&
#70000
1!
1"
1%
