ALU/alu.v
// alu
// we design alu for  8 bit and it will perform the below function:
// 	addition
// 	subtraction
// 	and
// 	or
// 	xor
// 	left and right shift


module alu(
	input wire[7:0] a, b, // take input
	input wire[2:0] select, // control or func selector
	output reg[7:0] out 
);

// define the alu operation

parameter ADD 		= 0;
parameter SUB 		= 1;
parameter ANDING 	= 2;
parameter ORING 	= 3;
parameter XORING 	= 4;
parameter LEFT_SHIFT 	= 5;
parameter RIGHT_SHIFT 	= 6;

always @(a or b or select)
	case(select)
		ADD: 		out = a + b;
		SUB: 		out = a - b;
		ANDING: 	out = a & b;
		ORING: 		out = a | b;
		XORING: 	out = a ^ b;
		LEFT_SHIFT: 	out = a << b;
		RIGHT_SHIFT: 	out = a >> b;
		default: 	out = 0;
	endcase
endmodule

ALU/alu_tb.v
// test batch for alu 
// give input and check the output with display statemetn


module alu_tb;

reg[7:0] a, b;
reg[2:0] select;
wire[7:0] out;

// instatiate alu func

alu uut(.a(a), .b(b), .select(select), .out(out));

initial begin
	$dumpfile("wave_alu.vcd");
	$dumpvars(0, alu_tb);

	a = 8'b00001111; b = 8'b00000011;
	for(select =0; select < 7; select = select +1) begin
		#10 $display("select: %b | a: %b | b: %b | out: %b", select, a, b, out);
	end
end
endmodule

ALU/wave_alu.vcd
$date
	Wed Feb 19 01:34:28 2025
$end
$version
	Icarus Verilog
$end
$timescale
	1s
$end
$scope module alu_tb $end
$var wire 8 ! out [7:0] $end
$var reg 8 " a [7:0] $end
$var reg 8 # b [7:0] $end
$var reg 3 $ select [2:0] $end
$scope module uut $end
$var wire 8 % a [7:0] $end
$var wire 8 & b [7:0] $end
$var wire 3 ' select [2:0] $end
$var reg 8 ( out [7:0] $end
$upscope $end
$upscope $end
$enddefinitions $end
#0
$dumpvars
b10010 (
b0 '
b11 &
b1111 %
b0 $
b11 #
b1111 "
b10010 !
$end
#10
b1100 (
b1100 !
b1 $
b1 '
#20
b11 (
b11 !
b10 $
b10 '
#30
b1111 (
b1111 !
b11 $
b11 '
#40
b1100 (
b1100 !
b100 $
b100 '
#50
b1111000 (
b1111000 !
b101 $
b101 '
#60
b1 (
b1 !
b110 $
b110 '
#70
b0 (
b0 !
b111 $
b111 '
